taschenmesser/__init__.py
taschenmesser/_version.py
taschenmesser/aws.py
taschenmesser/fileutil.py
taschenmesser/gclosure.py
taschenmesser/pyegg.py
taschenmesser/svg.py
taschenmesser-18.3.2.dist-info/DESCRIPTION.rst
taschenmesser-18.3.2.dist-info/METADATA
taschenmesser-18.3.2.dist-info/RECORD
taschenmesser-18.3.2.dist-info/WHEEL
taschenmesser-18.3.2.dist-info/metadata.json
taschenmesser-18.3.2.dist-info/top_level.txt
