Metadata-Version: 2.0
Name: taschenmesser
Version: 18.3.2
Summary: Taschenmesser, a toolbelt with plugins for SCons
Home-page: http://www.tavendo.de
Author: Tavendo GmbH
Author-email: contact@tavendo.de
License: Apache License 2.0
Keywords: scons svg s3 aws
Platform: Any
Classifier: License :: OSI Approved :: Apache Software License
Classifier: Development Status :: 4 - Beta
Classifier: Environment :: Console
Classifier: Framework :: Twisted
Classifier: Intended Audience :: Developers
Classifier: Intended Audience :: System Administrators
Classifier: Operating System :: OS Independent
Classifier: Programming Language :: Python
Classifier: Topic :: Database
Classifier: Topic :: Internet
Classifier: Topic :: Software Development
Classifier: Topic :: Software Development :: Build Tools
Classifier: Topic :: Software Development :: Testing
Classifier: Topic :: System :: Systems Administration
Classifier: Topic :: Utilities
Provides-Extra: aws
Provides-Extra: svg
Requires-Dist: setuptools
Provides-Extra: aws
Requires-Dist: boto; extra == 'aws'
Provides-Extra: svg
Requires-Dist: scour (==0.33); extra == 'svg'
